smpw.py
smpw-1.1.3.dist-info/WHEEL
smpw-1.1.3.dist-info/METADATA
smpw-1.1.3.dist-info/RECORD
