Metadata-Version: 2.1
Name: smpw
Version: 1.1.3
Summary: hi my name Azarov Nick and i programist modile
Author: John Smith
Author-email: azarovnick@bk.ru
Requires-Python: >=3.8,<4.0
Classifier: Programming Language :: Python :: 3
Classifier: Programming Language :: Python :: 3.8
Classifier: Programming Language :: Python :: 3.9
